AUTHORS
LICENSE
MANIFEST.in
README.rst
ez_setup.py
setup.py
bin/pypit
pypit/__init__.py
pypit/pypit.py
pypit.egg-info/PKG-INFO
pypit.egg-info/SOURCES.txt
pypit.egg-info/dependency_links.txt
pypit.egg-info/not-zip-safe
pypit.egg-info/requires.txt
pypit.egg-info/top_level.txt
tests/test_file.txt
tests/test_file.txt.bla
tests/test_file.txt.buf
tests/test_pypit.py
tests/test_pypit.pyc
tests/{{ouput}}